slotpy/__init__.py
slotpy/buildgui.py
slotpy/dataframe.py
slotpy/plotter.py
slotpy/pictures/__init__.py
slotpy-0.0.8.dist-info/LICENCE.md
slotpy-0.0.8.dist-info/METADATA
slotpy-0.0.8.dist-info/WHEEL
slotpy-0.0.8.dist-info/top_level.txt
slotpy-0.0.8.dist-info/RECORD
