Metadata-Version: 2.1
Name: slotpy
Version: 0.0.8
Summary: Sliders and Plots
Home-page: https://github.com/Chia-vie/slotpy
Author: Laura Ketzer, Christine Ackerl, George Paraschos
Author-email: lketzer@aip.de, christine.ackerl@univie.ac.at, gfparaschos@mpifr.de
License: BSD
Keywords: astronomy,plotting,...
Platform: UNKNOWN
Classifier: Intended Audience :: Science/Research
Classifier: Topic :: Scientific/Engineering :: Astronomy
Classifier: License :: OSI Approved :: BSD License
Requires-Dist: numpy
Requires-Dist: pandas
Requires-Dist: matplotlib
Requires-Dist: vaex
Requires-Dist: tk
Requires-Dist: plotly
Requires-Dist: jupyter
